xml2rfc/__init__.py
xml2rfc/boilerplate_id_guidelines.py
xml2rfc/boilerplate_rfc_7841.py
xml2rfc/boilerplate_tlp.py
xml2rfc/debug.py
xml2rfc/log.py
xml2rfc/parser.py
xml2rfc/run.py
xml2rfc/scripts.py
xml2rfc/strings.py
xml2rfc/utils.py
xml2rfc/walkpdf.py
xml2rfc/data/SVG-1.2-RFC.rnc
xml2rfc/data/SVG-1.2-RFC.rng
xml2rfc/data/Scripts.txt
xml2rfc/data/metadata.js
xml2rfc/data/metadata.min.js
xml2rfc/data/reference.rnc
xml2rfc/data/reference.rng
xml2rfc/data/referencegroup.rnc
xml2rfc/data/referencegroup.rng
xml2rfc/data/rfc7991.rnc
xml2rfc/data/rfc7991.rng
xml2rfc/data/v2.rnc
xml2rfc/data/v2.rng
xml2rfc/data/v3.rnc
xml2rfc/data/v3.rng
xml2rfc/data/xml2rfc-v3-emacs-nxml.rnc
xml2rfc/data/xml2rfc.css
xml2rfc/data/xml2rfc.js
xml2rfc/templates/address_card.html
xml2rfc/templates/base.html
xml2rfc/templates/doc.xml
xml2rfc/templates/doc.yaml
xml2rfc/templates/rfc2629-other.ent
xml2rfc/templates/rfc2629-xhtml.ent
xml2rfc/templates/rfc2629.dtd
xml2rfc/uniscripts/__init__.py
xml2rfc/uniscripts/unidata.py
xml2rfc/uniscripts/update/make_unidata.py
xml2rfc/util/__init__.py
xml2rfc/util/date.py
xml2rfc/util/file.py
xml2rfc/util/fonts.py
xml2rfc/util/name.py
xml2rfc/util/num.py
xml2rfc/util/postal.py
xml2rfc/util/unicode.py
xml2rfc/writers/__init__.py
xml2rfc/writers/base.py
xml2rfc/writers/bib.py
xml2rfc/writers/doc.py
xml2rfc/writers/expand.py
xml2rfc/writers/expanded_xml.py
xml2rfc/writers/html.py
xml2rfc/writers/legacy_html.py
xml2rfc/writers/nroff.py
xml2rfc/writers/paginated_txt.py
xml2rfc/writers/pdf.py
xml2rfc/writers/preptool.py
xml2rfc/writers/raw_txt.py
xml2rfc/writers/text.py
xml2rfc/writers/unprep.py
xml2rfc/writers/v2v3.py
xml2rfc-3.31.0.dist-info/licenses/LICENSE
xml2rfc-3.31.0.dist-info/METADATA
xml2rfc-3.31.0.dist-info/WHEEL
xml2rfc-3.31.0.dist-info/entry_points.txt
xml2rfc-3.31.0.dist-info/top_level.txt
xml2rfc-3.31.0.dist-info/RECORD
