Metadata-Version: 2.4
Name: xml2rfc
Version: 3.31.0
Summary: xml2rfc generates RFCs and IETF drafts from document source in XML according to the IETF xml2rfc v2 and v3 vocabularies.
Author-email: IETF Tools <tools-help@ietf.org>
License-Expression: BSD-3-Clause
Project-URL: homepage, https://github.com/ietf-tools/xml2rfc
Project-URL: source, https://github.com/ietf-tools/xml2rfc
Project-URL: changelog, https://github.com/ietf-tools/xml2rfc/blob/main/CHANGELOG.md
Project-URL: releasenotes, https://github.com/ietf-tools/xml2rfc/releases
Project-URL: documentation, https://authors.ietf.org/en/rfcxml-vocabulary
Project-URL: issues, https://github.com/ietf-tools/xml2rfc/issues
Keywords: ietf,rfc,id,internet-draft,xml,xml2rfc,xmlrfc
Classifier: Development Status :: 5 - Production/Stable
Classifier: Environment :: Console
Classifier: Operating System :: MacOS :: MacOS X
Classifier: Operating System :: Microsoft :: Windows
Classifier: Operating System :: POSIX :: Linux
Classifier: Programming Language :: Python
Classifier: Topic :: Text Processing
Classifier: Topic :: Text Processing :: Markup :: XML
Classifier: Programming Language :: Python :: 3.9
Classifier: Programming Language :: Python :: 3.10
Classifier: Programming Language :: Python :: 3.11
Classifier: Programming Language :: Python :: 3.12
Classifier: Programming Language :: Python :: 3.13
Classifier: Programming Language :: Python :: 3.14
Requires-Python: >=3.9
License-File: LICENSE
Requires-Dist: platformdirs>=3.6.0
Requires-Dist: configargparse>=1.2.3
Requires-Dist: google-i18n-address>=3.0.0
Requires-Dist: intervaltree>=3.1.0
Requires-Dist: jinja2>=3.1.2
Requires-Dist: lxml>=5.3.0
Requires-Dist: pycountry>=22.3.5
Requires-Dist: pyyaml>=5.3.1
Requires-Dist: requests>=2.5.0
Requires-Dist: wcwidth>=0.2.5
Provides-Extra: pdf
Requires-Dist: weasyprint==65.0; extra == "pdf"
Provides-Extra: tests
Requires-Dist: decorator; extra == "tests"
Requires-Dist: dict2xml; extra == "tests"
Requires-Dist: pyflakes; extra == "tests"
Requires-Dist: pypdf>=4.1.0; extra == "tests"
Requires-Dist: tox; extra == "tests"
Requires-Dist: xml2rfc[pdf]; sys_platform != "win32" and extra == "tests"
Dynamic: license-file
